odoo/addons/ssi_fixed_asset_in_progress/README.rst
odoo/addons/ssi_fixed_asset_in_progress/__init__.py
odoo/addons/ssi_fixed_asset_in_progress/__manifest__.py
odoo/addons/ssi_fixed_asset_in_progress/data/account_journal_data.xml
odoo/addons/ssi_fixed_asset_in_progress/data/account_type_demo.xml
odoo/addons/ssi_fixed_asset_in_progress/data/approval_template_data.xml
odoo/addons/ssi_fixed_asset_in_progress/data/ir_sequence_data.xml
odoo/addons/ssi_fixed_asset_in_progress/data/policy_template_data.xml
odoo/addons/ssi_fixed_asset_in_progress/data/sequence_template_data.xml
odoo/addons/ssi_fixed_asset_in_progress/demo/account_account_demo.xml
odoo/addons/ssi_fixed_asset_in_progress/demo/account_journal_demo.xml
odoo/addons/ssi_fixed_asset_in_progress/demo/fixed_asset_category_demo.xml
odoo/addons/ssi_fixed_asset_in_progress/i18n/id.po
odoo/addons/ssi_fixed_asset_in_progress/i18n/ssi_fixed_asset_in_progress.pot
odoo/addons/ssi_fixed_asset_in_progress/models/__init__.py
odoo/addons/ssi_fixed_asset_in_progress/models/account_move_line.py
odoo/addons/ssi_fixed_asset_in_progress/models/fixed_asset_asset.py
odoo/addons/ssi_fixed_asset_in_progress/models/fixed_asset_category.py
odoo/addons/ssi_fixed_asset_in_progress/models/fixed_asset_in_progress.py
odoo/addons/ssi_fixed_asset_in_progress/security/ir.model.access.csv
odoo/addons/ssi_fixed_asset_in_progress/security/ir_module_category_data.xml
odoo/addons/ssi_fixed_asset_in_progress/security/ir_rule_data.xml
odoo/addons/ssi_fixed_asset_in_progress/security/res_group_data.xml
odoo/addons/ssi_fixed_asset_in_progress/static/description/banner.png
odoo/addons/ssi_fixed_asset_in_progress/static/description/icon.png
odoo/addons/ssi_fixed_asset_in_progress/views/fixed_asset_category_views.xml
odoo/addons/ssi_fixed_asset_in_progress/views/fixed_asset_in_progress_views.xml
odoo14_addon_ssi_fixed_asset_in_progress-14.0.1.3.0.dist-info/METADATA
odoo14_addon_ssi_fixed_asset_in_progress-14.0.1.3.0.dist-info/WHEEL
odoo14_addon_ssi_fixed_asset_in_progress-14.0.1.3.0.dist-info/top_level.txt
odoo14_addon_ssi_fixed_asset_in_progress-14.0.1.3.0.dist-info/RECORD
